pyzagi/__init__.py
pyzagi/__version__.py
pyzagi/examples.py
pyzagi/pz.py
pyzagi/pztools.py
pyzagi-0.1.0.dist-info/METADATA
pyzagi-0.1.0.dist-info/WHEEL
pyzagi-0.1.0.dist-info/licenses/LICENSE
pyzagi-0.1.0.dist-info/RECORD
